{
  "@@review_requested": NaN,
  "@context": "TBD",
  "branded_variable": "swhswell_tavg-z0-hxy-sea",
  "cell_methods": "area: mean where sea time: mean",
  "cmip6_compound_name": "6hr.swhswell",
  "description": "Average height of the highest one-third of waves present in the sea state, incorporating just swell waves (i.e., waves that have propagated away from their generation area). This parameter is derived from all swell partitions of the wave spectrum using spectral moments. Specifically, this parameter is four times the square root of the integral over all directions and all frequencies of the\u00a0components of the two-dimensional wave spectrum that are not under the influence of local wind.",
  "dimensions": [
    "longitude",
    "latitude",
    "time"
  ],
  "id": "TBD",
  "label": "TBD",
  "type": [
    "TBD"
  ],
  "variableRootDD": "swhswell"
}