{
  "@@review_requested": NaN,
  "@context": "TBD",
  "branded_variable": "cli_tavg-l-hxy-x",
  "cell_methods": "area: time: mean",
  "cmip6_compound_name": "Amon.cli",
  "description": "Includes both large-scale and convective cloud.  This is calculated as the mass of cloud ice in the grid cell divided by the mass of air (including the water in all phases) in the grid cell. It includes precipitating hydrometeors ONLY if the precipitating hydrometeors affect the calculation of radiative transfer in model.",
  "dimensions": [
    "longitude",
    "latitude",
    "alevel",
    "time"
  ],
  "id": "TBD",
  "label": "TBD",
  "type": [
    "TBD"
  ],
  "variableRootDD": "cli"
}