{
  "@@review_requested": NaN,
  "@context": "TBD",
  "branded_variable": "ccldncl_tavg-z0-hxy-ccl",
  "cell_methods": "area: time: mean where convective_cloud (but only in upper-most layer of convective liquid water cloud and weighted by area of convective liquid water cloud top as seen from TOA)",
  "cmip6_compound_name": "Emon.ccldncl",
  "description": "Cloud Droplet Number Concentration of Convective Cloud Tops",
  "dimensions": [
    "longitude",
    "latitude",
    "time"
  ],
  "id": "TBD",
  "label": "TBD",
  "type": [
    "TBD"
  ],
  "variableRootDD": "ccldncl"
}